ivcap_df/__init__.py
ivcap_df/column.py
ivcap_df/connector.py
ivcap_df/cozo/__init__.py
ivcap_df/cozo/cozo_connector.py
ivcap_df/dataSet.py
ivcap_df/ivcap/__init__.py
ivcap_df/ivcap/ivcap_connector.py
ivcap_df/schema.py
ivcap_df/sql/__init__.py
ivcap_df/sql/ivap_sql.py
ivcap_df/sql/sql_connector.py
ivcap_df/types.py
ivcap_df-0.4.0.dist-info/LICENSE
ivcap_df-0.4.0.dist-info/METADATA
ivcap_df-0.4.0.dist-info/WHEEL
ivcap_df-0.4.0.dist-info/RECORD
