Metadata-Version: 2.1
Name: ivcap-df
Version: 0.4.0
Summary: Library to model, search, and work with linked data in IVCAP
License: BSD-3
Author: Max Ott
Author-email: max.ott@csiro.au
Requires-Python: >=3.9,<4.0
Classifier: License :: Other/Proprietary License
Classifier: Programming Language :: Python :: 3
Classifier: Programming Language :: Python :: 3.9
Classifier: Programming Language :: Python :: 3.10
Classifier: Programming Language :: Python :: 3.11
Requires-Dist: graphviz (>=0.20.1,<0.21.0)
Requires-Dist: ivcap_client (>=0.28.0)
Requires-Dist: pandas (>=2.0.0,<3.0.0)
